llmaid/__init__.py
llmaid/client.py
llmaid/core.py
llmaid/exceptions.py
llmaid-0.1.1.dist-info/licenses/LICENSE.md
llmaid-0.1.1.dist-info/METADATA
llmaid-0.1.1.dist-info/WHEEL
llmaid-0.1.1.dist-info/top_level.txt
llmaid-0.1.1.dist-info/RECORD
