Metadata-Version: 2.4
Name: llmaid
Version: 0.1.1
Summary: A zero‑dependency wrapper that turns any OpenAI‑compatible endpoint into a hackable one‑liner.
Author: ant-strudel
License: MIT
Project-URL: Homepage, https://github.com/ant-strudl/llmaid
Project-URL: Documentation, https://github.com/ant-strudl/llmaid/blob/main/docs/Public%20API%20Reference.md
Project-URL: Repository, https://github.com/ant-strudl/llmaid
Project-URL: Bug Tracker, https://github.com/ant-strudl/llmaid/issues
Keywords: llm,ai,client,openai,anthropic
Classifier: Development Status :: 3 - Alpha
Classifier: Intended Audience :: Developers
Classifier: License :: OSI Approved :: MIT License
Classifier: Programming Language :: Python :: 3
Classifier: Programming Language :: Python :: 3.8
Classifier: Programming Language :: Python :: 3.9
Classifier: Programming Language :: Python :: 3.10
Classifier: Programming Language :: Python :: 3.11
Classifier: Programming Language :: Python :: 3.12
Classifier: Topic :: Software Development :: Libraries :: Python Modules
Classifier: Topic :: Scientific/Engineering :: Artificial Intelligence
Requires-Python: >=3.8
License-File: LICENSE.md
Requires-Dist: httpx>=0.24.0
Requires-Dist: pydantic>=2.0.0
Requires-Dist: PyYAML>=6.0
Provides-Extra: dev
Requires-Dist: pytest>=7.0.0; extra == "dev"
Requires-Dist: pytest-asyncio>=0.21.0; extra == "dev"
Requires-Dist: pytest-httpx>=0.21.0; extra == "dev"
Requires-Dist: black>=23.0.0; extra == "dev"
Requires-Dist: flake8>=6.0.0; extra == "dev"
Requires-Dist: mypy>=1.0.0; extra == "dev"
Dynamic: license-file
